agentic_sdk/__init__.py
agentic_sdk/agent.py
agentic_sdk/audio.py
agentic_sdk/config.py
agentic_sdk/state.py
agentic_sdk/transcript.py
ai_convo_simulator-0.1.0.dist-info/METADATA
ai_convo_simulator-0.1.0.dist-info/WHEEL
ai_convo_simulator-0.1.0.dist-info/top_level.txt
ai_convo_simulator-0.1.0.dist-info/RECORD
