Metadata-Version: 2.4
Name: ai-convo-simulator
Version: 0.1.0
Summary: SDK to simulate 2-person AI conversations with audio and text output using LangGraph.
Author-email: SreenivasuAkella <210020001@iitdh.ac.in>
License: MIT
Requires-Python: >=3.10
Requires-Dist: openai
Requires-Dist: langchain
Requires-Dist: langchain-community
Requires-Dist: langchain-openai
Requires-Dist: langgraph
Requires-Dist: traceai-langchain
Requires-Dist: pydantic
Requires-Dist: pyyaml
Requires-Dist: soundfile
Requires-Dist: coqui-tts
Requires-Dist: gtts
Requires-Dist: python-dotenv
Provides-Extra: dev
Requires-Dist: pytest; extra == "dev"
Requires-Dist: black; extra == "dev"
Requires-Dist: ruff; extra == "dev"
